Metadata-Version: 1.0
Name: BayesianLinearRegression
Version: 0.1.2
Summary: Fits Linear and Logistic Regression Models using MCMC.
Home-page: UNKNOWN
Author: John Clements
Author-email: blr.johnclements@gmail.com
License: UNKNOWN
Platform: UNKNOWN
